<PAMDataset>
  <Metadata>
    <MDI key="DataType">Generic</MDI>
  </Metadata>
  <Metadata domain="Esri">
    <MDI key="PyramidResamplingType">NEAREST</MDI>
  </Metadata>
  <PAMRasterBand band="1">
    <Histograms>
      <HistItem>
        <HistMin>0</HistMin>
        <HistMax>894.1195678710938</HistMax>
        <BucketCount>256</BucketCount>
        <IncludeOutOfRange>1</IncludeOutOfRange>
        <Approximate>0</Approximate>
        <HistCounts>434|739|3250|5734|7495|7970|7058|6693|6205|5720|5547|5129|4556|4260|3660|3322|3172|3153|3229|3062|2753|2648|2259|2095|1906|1731|1654|1545|1459|1299|1188|1144|1056|1080|969|934|852|916|909|886|857|834|834|846|813|826|830|813|878|844|866|907|856|853|861|921|887|980|976|1032|916|950|906|939|922|872|910|914|858|861|846|788|761|764|737|661|709|683|638|621|594|617|569|579|541|570|534|518|476|508|500|475|432|393|398|414|411|414|396|375|353|346|373|360|359|337|380|349|351|387|389|407|375|389|359|373|329|337|292|298|284|281|267|244|222|235|223|217|230|212|224|212|250|230|220|231|249|250|241|230|235|243|242|238|238|214|215|171|162|172|176|190|185|186|176|189|196|186|189|211|197|203|200|156|176|154|153|134|176|159|141|139|117|109|94|114|97|57|69|55|36|34|37|19|17|22|20|12|15|6|7|8|7|0|4|5|3|4|3|2|4|0|1|0|4|2|2|2|4|0|1|1|1|1|2|0|0|2|1|0|0|0|0|0|0|0|0|1|0|0|1|0|0|0|0|0|1|0|0|1|0|0|0|0|0|0|0|0|0|0|0|0|0|0|0|1</HistCounts>
      </HistItem>
    </Histograms>
    <Metadata>
      <MDI key="SourceBandIndex">0</MDI>
      <MDI key="STATISTICS_COVARIANCES">20521.20144595898</MDI>
      <MDI key="STATISTICS_EXCLUDEDVALUES"></MDI>
      <MDI key="STATISTICS_MAXIMUM">894.11956787109</MDI>
      <MDI key="STATISTICS_MEAN">136.22333139629</MDI>
      <MDI key="STATISTICS_MINIMUM">0</MDI>
      <MDI key="STATISTICS_SKIPFACTORX">1</MDI>
      <MDI key="STATISTICS_SKIPFACTORY">1</MDI>
      <MDI key="STATISTICS_STDDEV">143.25223016051</MDI>
    </Metadata>
  </PAMRasterBand>
</PAMDataset>
